{
  "project_info": {
    "project_number": "636275774602",
    "project_id": "fir-garcia-2a877",
    "storage_bucket": "fir-garcia-2a877.firebasestorage.app"
  },
  "client": [
    {
      "client_info": {
        "mobilesdk_app_id": "1:636275774602:android:f1c51a44f2b08cae26c973",
        "android_client_info": {
          "package_name": "utez.edu.mx"
        }
      },
      "oauth_client": [],
      "api_key": [
        {
          "current_key": "AIzaSyAivXwgDKvi026pHg_QFD4XCpOjg8Wa5tk"
        }
      ],
      "services": {
        "appinvite_service": {
          "other_platform_oauth_client": []
        }
      }
    }
  ],
  "configuration_version": "1"
}